anovos/__init__.py
anovos/__main__.py
anovos/version.py
anovos/workflow.py
anovos/data_analyzer/__init__.py
anovos/data_analyzer/association_eval_varclus.py
anovos/data_analyzer/association_evaluator.py
anovos/data_analyzer/geospatial_analyzer.py
anovos/data_analyzer/quality_checker.py
anovos/data_analyzer/stats_generator.py
anovos/data_analyzer/ts_analyzer.py
anovos/data_ingest/__init__.py
anovos/data_ingest/data_ingest.py
anovos/data_ingest/data_sampling.py
anovos/data_ingest/geo_auto_detection.py
anovos/data_ingest/ts_auto_detection.py
anovos/data_report/__init__.py
anovos/data_report/basic_report_generation.py
anovos/data_report/report_generation.py
anovos/data_report/report_preprocessing.py
anovos/data_transformer/__init__.py
anovos/data_transformer/datetime.py
anovos/data_transformer/geo_utils.py
anovos/data_transformer/geospatial.py
anovos/data_transformer/transformers.py
anovos/drift_stability/__init__.py
anovos/drift_stability/drift_detector.py
anovos/drift_stability/stability.py
anovos/drift_stability/validations.py
anovos/feature_recommender/__init__.py
anovos/feature_recommender/featrec_init.py
anovos/feature_recommender/feature_explorer.py
anovos/feature_recommender/feature_mapper.py
anovos/feature_recommender/data/flatten_fr_db.csv
anovos/feature_store/__init__.py
anovos/feature_store/feast_exporter.py
anovos/feature_store/feature_retrieval.py
anovos/shared/__init__.py
anovos/shared/spark.py
anovos/shared/utils.py
anovos-1.1.0.dist-info/LICENSE
anovos-1.1.0.dist-info/METADATA
anovos-1.1.0.dist-info/WHEEL
anovos-1.1.0.dist-info/top_level.txt
anovos-1.1.0.dist-info/RECORD
