Metadata-Version: 2.1
Name: anovos
Version: 1.1.0
Summary: An Open Source tool for Feature Engineering in Machine Learning
Home-page: https://github.com/anovos/anovos.git
Author: Team Anovos
Author-email: info@anovos.ai
Keywords: machine learning,open source,feature engineering,analytics,apache spark,feature recommendation
Requires-Python: >=3.7
License-File: LICENSE
Requires-Dist: black (==22.10.0)
Requires-Dist: pandas (<1.5.3,>=1.2.5)
Requires-Dist: numpy (<1.23.6,>=1.20.0)
Requires-Dist: scipy (<1.10.0)
Requires-Dist: scikit-learn (==1.0.2)
Requires-Dist: sympy (<1.12,>=1.6)
Requires-Dist: matplotlib (<3.5.4,>=3.4.3)
Requires-Dist: plotly (==5.7.0)
Requires-Dist: datapane (==0.15.3)
Requires-Dist: pyarrow (<11.0.0)
Requires-Dist: findspark (==2.0.1)
Requires-Dist: loguru (==0.6.0)
Requires-Dist: pyaml (==21.10.1)
Requires-Dist: isort (==5.10.1)
Requires-Dist: boto3
Requires-Dist: cython
Requires-Dist: pygeohash (==1.2.0)
Requires-Dist: s3path
Requires-Dist: s3fs
Requires-Dist: pybind11
Requires-Dist: fsspec
Requires-Dist: py4j
Requires-Dist: popmon
Requires-Dist: varclushi
Requires-Dist: reverse-geocoder
Requires-Dist: tensorflow
Requires-Dist: soupsieve
Requires-Dist: statsmodels (==0.13.5)
Requires-Dist: sentence-transformers
Requires-Dist: mlflow (==1.27.0)
Requires-Dist: geopy (==2.3.0)
Requires-Dist: geohash2 (==1.1)
Requires-Dist: geojson (==2.5.0)
